{
    "english": [
        "Search No",
        "Reference model",
        "Contents",
        "Before correction",
        "After correction",
        "Model Name",
        "Target Part Name",
        "Motor Specification",
        "Issue Classification",
        "Update Info",
        "Upload Date",
        "Added By"
    ],
    "japanese": [
        "検索No.",
        "参考機種",
        "内容",
        "訂正前",
        "訂正後",
        "機種名",
        "対象部品名",
        "モータ仕様",
        "指摘項目の分類",
        "更新情報",
        "アップロード日",
        "追加者"
    ],
    "visible": {
        "Search No": true,
        "Reference model": true,
        "Contents": false,
        "Before correction": false,
        "After correction": false,
        "Model Name": true,
        "Target Part Name": true,
        "Motor Specification": true,
        "Issue Classification": true,
        "Update Info": true,
        "Upload Date": false,
        "Added By": false
    }
}